Workbook

Sheet Payments
A1: Client ID | B1: Lead ID | C1: Venture | D1: Business Name | E1: Project Type | F1: Project Price | G1: Deposit Percentage | H1: Deposit Amount | I1: Deposit Invoice Date | J1: Deposit Due Date | K1: Deposit Status | L1: Deposit Paid Date | M1: Final Payment Amount | N1: Final Invoice Date | O1: Final Due Date | P1: Final Payment Status | Q1: Final Paid Date | R1: Recurring Monthly Fee | S1: Recurring Revenue Start Date | T1: Next Recurring Payment | U1: Recurring Payment Status | V1: Total Invoiced | W1: Total Collected | X1: Outstanding Balance | Y1: Payment Link | Z1: Notes
A2: CLIENT-001 | B2: LEAD-001 | C2: Web Development | D2: Example: Riverside Family Dental | E2: Standard Website | F2: 1200 | G2: 0.5 | H2: =IF(OR(F2="",G2=""),"",F2*G2) -> 600 | I2: 46294 | J2: 46301 | K2: Paid | L2: 46296 | M2: =IF(F2="","",F2-H2) -> 600 | P2: Not Invoiced | R2: 39 | U2: N/A | V2: =(IF(AND(K2<>"Not Invoiced",H2<>""),H2,0))+(IF(AND(P2<>"Not Invoiced",M2<>""),M2,0)) -> 600 | W2: =(IF(K2="Paid",H2,0))+(IF(P2="Paid",M2,0))+(IF(U2="Active",R2,0)) -> 600 | X2: =IF(V2="","",V2-W2) -> 0 | Y2: {{PAYMENT_LINK_PLACEHOLDER}} | Z2: Fictional example row — safe to delete. Deposit paid; site in build.
A3: CLIENT-002 | B3: LEAD-002 | C3: Cinematic Videos | D3: Example: Bluestone Realty Group | E3: Cinematic Property Film | F3: 1800 | G3: 0.5 | H3: =IF(OR(F3="",G3=""),"",F3*G3) -> 900 | I3: 46285 | J3: 46292 | K3: Invoiced | M3: =IF(F3="","",F3-H3) -> 900 | P3: Not Invoiced | U3: N/A | V3: =(IF(AND(K3<>"Not Invoiced",H3<>""),H3,0))+(IF(AND(P3<>"Not Invoiced",M3<>""),M3,0)) -> 900 | W3: =(IF(K3="Paid",H3,0))+(IF(P3="Paid",M3,0))+(IF(U3="Active",R3,0)) -> 0 | X3: =IF(V3="","",V3-W3) -> 900 | Y3: {{PAYMENT_LINK_PLACEHOLDER}} | Z3: Fictional example row — safe to delete. Awaiting deposit.
H4: =IF(OR(F4="",G4=""),"",F4*G4) | M4: =IF(F4="","",F4-H4) | V4: =(IF(AND(K4<>"Not Invoiced",H4<>""),H4,0))+(IF(AND(P4<>"Not Invoiced",M4<>""),M4,0)) -> 0 | W4: =(IF(K4="Paid",H4,0))+(IF(P4="Paid",M4,0))+(IF(U4="Active",R4,0)) -> 0 | X4: =IF(V4="","",V4-W4) -> 0
H5: =IF(OR(F5="",G5=""),"",F5*G5) | M5: =IF(F5="","",F5-H5) | V5: =(IF(AND(K5<>"Not Invoiced",H5<>""),H5,0))+(IF(AND(P5<>"Not Invoiced",M5<>""),M5,0)) -> 0 | W5: =(IF(K5="Paid",H5,0))+(IF(P5="Paid",M5,0))+(IF(U5="Active",R5,0)) -> 0 | X5: =IF(V5="","",V5-W5) -> 0
H6: =IF(OR(F6="",G6=""),"",F6*G6) | M6: =IF(F6="","",F6-H6) | V6: =(IF(AND(K6<>"Not Invoiced",H6<>""),H6,0))+(IF(AND(P6<>"Not Invoiced",M6<>""),M6,0)) -> 0 | W6: =(IF(K6="Paid",H6,0))+(IF(P6="Paid",M6,0))+(IF(U6="Active",R6,0)) -> 0 | X6: =IF(V6="","",V6-W6) -> 0
H7: =IF(OR(F7="",G7=""),"",F7*G7) | M7: =IF(F7="","",F7-H7) | V7: =(IF(AND(K7<>"Not Invoiced",H7<>""),H7,0))+(IF(AND(P7<>"Not Invoiced",M7<>""),M7,0)) -> 0 | W7: =(IF(K7="Paid",H7,0))+(IF(P7="Paid",M7,0))+(IF(U7="Active",R7,0)) -> 0 | X7: =IF(V7="","",V7-W7) -> 0
H8: =IF(OR(F8="",G8=""),"",F8*G8) | M8: =IF(F8="","",F8-H8) | V8: =(IF(AND(K8<>"Not Invoiced",H8<>""),H8,0))+(IF(AND(P8<>"Not Invoiced",M8<>""),M8,0)) -> 0 | W8: =(IF(K8="Paid",H8,0))+(IF(P8="Paid",M8,0))+(IF(U8="Active",R8,0)) -> 0 | X8: =IF(V8="","",V8-W8) -> 0
H9: =IF(OR(F9="",G9=""),"",F9*G9) | M9: =IF(F9="","",F9-H9) | V9: =(IF(AND(K9<>"Not Invoiced",H9<>""),H9,0))+(IF(AND(P9<>"Not Invoiced",M9<>""),M9,0)) -> 0 | W9: =(IF(K9="Paid",H9,0))+(IF(P9="Paid",M9,0))+(IF(U9="Active",R9,0)) -> 0 | X9: =IF(V9="","",V9-W9) -> 0
H10: =IF(OR(F10="",G10=""),"",F10*G10) | M10: =IF(F10="","",F10-H10) | V10: =(IF(AND(K10<>"Not Invoiced",H10<>""),H10,0))+(IF(AND(P10<>"Not Invoiced",M10<>""),M10,0)) -> 0 | W10: =(IF(K10="Paid",H10,0))+(IF(P10="Paid",M10,0))+(IF(U10="Active",R10,0)) -> 0 | X10: =IF(V10="","",V10-W10) -> 0
H11: =IF(OR(F11="",G11=""),"",F11*G11) | M11: =IF(F11="","",F11-H11) | V11: =(IF(AND(K11<>"Not Invoiced",H11<>""),H11,0))+(IF(AND(P11<>"Not Invoiced",M11<>""),M11,0)) -> 0 | W11: =(IF(K11="Paid",H11,0))+(IF(P11="Paid",M11,0))+(IF(U11="Active",R11,0)) -> 0 | X11: =IF(V11="","",V11-W11) -> 0
H12: =IF(OR(F12="",G12=""),"",F12*G12) | M12: =IF(F12="","",F12-H12) | V12: =(IF(AND(K12<>"Not Invoiced",H12<>""),H12,0))+(IF(AND(P12<>"Not Invoiced",M12<>""),M12,0)) -> 0 | W12: =(IF(K12="Paid",H12,0))+(IF(P12="Paid",M12,0))+(IF(U12="Active",R12,0)) -> 0 | X12: =IF(V12="","",V12-W12) -> 0
H13: =IF(OR(F13="",G13=""),"",F13*G13) | M13: =IF(F13="","",F13-H13) | V13: =(IF(AND(K13<>"Not Invoiced",H13<>""),H13,0))+(IF(AND(P13<>"Not Invoiced",M13<>""),M13,0)) -> 0 | W13: =(IF(K13="Paid",H13,0))+(IF(P13="Paid",M13,0))+(IF(U13="Active",R13,0)) -> 0 | X13: =IF(V13="","",V13-W13) -> 0
H14: =IF(OR(F14="",G14=""),"",F14*G14) | M14: =IF(F14="","",F14-H14) | V14: =(IF(AND(K14<>"Not Invoiced",H14<>""),H14,0))+(IF(AND(P14<>"Not Invoiced",M14<>""),M14,0)) -> 0 | W14: =(IF(K14="Paid",H14,0))+(IF(P14="Paid",M14,0))+(IF(U14="Active",R14,0)) -> 0 | X14: =IF(V14="","",V14-W14) -> 0
H15: =IF(OR(F15="",G15=""),"",F15*G15) | M15: =IF(F15="","",F15-H15) | V15: =(IF(AND(K15<>"Not Invoiced",H15<>""),H15,0))+(IF(AND(P15<>"Not Invoiced",M15<>""),M15,0)) -> 0 | W15: =(IF(K15="Paid",H15,0))+(IF(P15="Paid",M15,0))+(IF(U15="Active",R15,0)) -> 0 | X15: =IF(V15="","",V15-W15) -> 0
... H151: =IF(OR(F151="",G151=""),"",F151*G151) | M151: =IF(F151="","",F151-H151) | V151: =(IF(AND(K151<>"Not Invoiced",H151<>""),H151,0))+(IF(AND(P151<>"Not Invoiced",M151<>""),M151,0)) -> 0 | W151: =(IF(K151="Paid",H151,0))+(IF(P151="Paid",M151,0))+(IF(U151="Active",R151,0)) -> 0 | X151: =IF(V151="","",V151-W151) -> 0

Sheet Totals Summary
A1: Payment Totals Summary
A3: Metric | B3: Web Development | C3: Cinematic Videos
A4: Total Invoiced | B4: =SUMIFS(Payments!$V$2:$V$151,Payments!$C$2:$C$151,"Web Development") -> 600 | C4: =SUMIFS(Payments!$V$2:$V$151,Payments!$C$2:$C$151,"Cinematic Videos") -> 900
A5: Total Collected | B5: =SUMIFS(Payments!$W$2:$W$151,Payments!$C$2:$C$151,"Web Development") -> 600 | C5: =SUMIFS(Payments!$W$2:$W$151,Payments!$C$2:$C$151,"Cinematic Videos") -> 0
A6: Outstanding Balance | B6: =SUMIFS(Payments!$X$2:$X$151,Payments!$C$2:$C$151,"Web Development") -> 0 | C6: =SUMIFS(Payments!$X$2:$X$151,Payments!$C$2:$C$151,"Cinematic Videos") -> 900
A7: Active Recurring Monthly Revenue | B7: =SUMIFS(Payments!$R$2:$R$151,Payments!$C$2:$C$151,"Web Development",Payments!$U$2:$U$151,"Active") -> 0 | C7: =SUMIFS(Payments!$R$2:$R$151,Payments!$C$2:$C$151,"Cinematic Videos",Payments!$U$2:$U$151,"Active") -> 0
A8: Overdue Deposits | B8: =COUNTIFS(Payments!$K$2:$K$151,"Overdue",Payments!$C$2:$C$151,"Web Development") -> 0 | C8: =COUNTIFS(Payments!$K$2:$K$151,"Overdue",Payments!$C$2:$C$151,"Cinematic Videos") -> 0
A9: Overdue Final Payments | B9: =COUNTIFS(Payments!$P$2:$P$151,"Overdue",Payments!$C$2:$C$151,"Web Development") -> 0 | C9: =COUNTIFS(Payments!$P$2:$P$151,"Overdue",Payments!$C$2:$C$151,"Cinematic Videos") -> 0
A10: Combined Total Invoiced | B10: =B4+C4 -> 1500
A11: Combined Total Collected | B11: =B5+C5 -> 600
A13: Copy the two 'Combined' figures above into the Master CRM dashboards and Weekly Dashboard's yellow 'Cash collected' cells each week.

Sheet Lists
A1: Venture | B1: ProjectType | C1: PaymentStatus | D1: RecurringStatus
A2: Web Development | B2: Standard Website | C2: Not Invoiced | D2: N/A
A3: Cinematic Videos | B3: Launch-Partner Website | C3: Invoiced | D3: Active
B4: Managed Hosting & Analytics | C4: Paid | D4: Paused
B5: Cinematic Property Film | C5: Overdue | D5: Cancelled
B6: Cinematic Location Film | C6: Waived | D6: Overdue
B7: Other
