Workbook

Sheet Master Pipeline Dashboard
A1: Master Pipeline Dashboard
A2: Combined operations view for Web Development + Cinematic Videos — Cashflow Ventures
A4: Venture Filter (KPI cards below): | B4: All | D4: Venture criteria (helper): | E4: =IF(B4="All","*",B4) -> *
A5: Combined Monthly Revenue Goal: | B5: ='Web Development Dashboard'!$B$5+'Cinematic Videos Dashboard'!$B$5 -> 8500
A7: Key Performance Indicators (filtered by Venture Filter above)
A8: Total leads | B8: =COUNTIFS('Master Leads'!$B$2:$B$201,$E$4) -> 2
A9: New leads this month | B9: =COUNTIFS('Master Leads'!$B$2:$B$201,$E$4,'Master Leads'!$C$2:$C$201,">="&EOMONTH(TODAY(),-1)+1,'Master Leads'!$C$2:$C$201,"<="&EOMONTH(TODAY(),0)) -> 0
A10: Prospects contacted | B10: =COUNTIFS('Master Leads'!$B$2:$B$201,$E$4,'Master Leads'!$V$2:$V$201,"<>") -> 2
A11: Follow-ups sent | B11: =COUNTIFS(Activities!$D$2:$D$201,$E$4,Activities!$G$2:$G$201,"Follow-Up Email") -> 0
A12: Positive replies | B12: =SUMPRODUCT(((($B$4="All")+('Master Leads'!$B$2:$B$201=$B$4))>0)*(ISNUMBER(MATCH('Master Leads'!$Y$2:$Y$201,{"Replied","Qualified","Preview Sent","Call Booked","Proposal Sent","Verbal Yes","Deposit Invoiced","Deposit Paid","Won"},0)))) -> 2
A13: Qualified leads | B13: =SUMPRODUCT(((($B$4="All")+('Master Leads'!$B$2:$B$201=$B$4))>0)*(ISNUMBER(MATCH('Master Leads'!$Y$2:$Y$201,{"Qualified","Preview Sent","Call Booked","Proposal Sent","Verbal Yes","Deposit Invoiced","Deposit Paid","Won"},0)))) -> 2
A14: Calls booked | B14: =SUMPRODUCT(((($B$4="All")+('Master Leads'!$B$2:$B$201=$B$4))>0)*(ISNUMBER(MATCH('Master Leads'!$Y$2:$Y$201,{"Call Booked","Proposal Sent","Verbal Yes","Deposit Invoiced","Deposit Paid","Won"},0)))) -> 2
A15: Previews created | B15: =SUMPRODUCT(((($B$4="All")+('Master Leads'!$B$2:$B$201=$B$4))>0)*(ISNUMBER(MATCH('Master Leads'!$U$2:$U$201,{"Ready","Sent","Viewed","Feedback Received"},0)))) -> 2
A16: Previews sent | B16: =SUMPRODUCT(((($B$4="All")+('Master Leads'!$B$2:$B$201=$B$4))>0)*(ISNUMBER(MATCH('Master Leads'!$U$2:$U$201,{"Sent","Viewed","Feedback Received"},0)))) -> 2
A17: Proposals sent | B17: =SUMPRODUCT(((($B$4="All")+('Master Leads'!$B$2:$B$201=$B$4))>0)*(ISNUMBER(MATCH('Master Leads'!$Y$2:$Y$201,{"Proposal Sent","Verbal Yes","Deposit Invoiced","Deposit Paid","Won"},0)))) -> 2
A18: Deals won | B18: =COUNTIFS('Master Leads'!$B$2:$B$201,$E$4,'Master Leads'!$Y$2:$Y$201,"Won") -> 0
A19: Deals lost | B19: =COUNTIFS('Master Leads'!$B$2:$B$201,$E$4,'Master Leads'!$Y$2:$Y$201,"Lost") -> 0
A20: Total pipeline value (open deals) | B20: =SUMIFS('Master Leads'!$Z$2:$Z$201,'Master Leads'!$B$2:$B$201,$E$4,'Master Leads'!$Y$2:$Y$201,"<>Won",'Master Leads'!$Y$2:$Y$201,"<>Lost") -> 3000
A21: Weighted pipeline | B21: =SUMIFS('Master Leads'!$AB$2:$AB$201,'Master Leads'!$B$2:$B$201,$E$4,'Master Leads'!$Y$2:$Y$201,"<>Won",'Master Leads'!$Y$2:$Y$201,"<>Lost") -> 1950
A22: Contracted revenue (Won deals) | B22: =SUMIFS('Master Leads'!$Z$2:$Z$201,'Master Leads'!$B$2:$B$201,$E$4,'Master Leads'!$Y$2:$Y$201,"Won") -> 0
A23: Cash collected (sync weekly from Payment Tracker) | B23: =B41+C41 -> 0
A24: Average deal value | B24: =IFERROR($B$22/COUNTIFS('Master Leads'!$B$2:$B$201,$E$4,'Master Leads'!$Y$2:$Y$201,"Won"),0) -> 0
A25: Reply rate | B25: =IFERROR($B$12/$B$10,0) -> 1
A26: Call-booking rate | B26: =IFERROR($B$14/$B$10,0) -> 1
A27: Proposal conversion rate | B27: =IFERROR($B$17/$B$14,0) -> 1
A28: Close rate | B28: =IFERROR($B$18/$B$17,0) -> 0
A29: Progress toward combined monthly revenue goal | B29: =IFERROR($B$22/$B$5,0) -> 0
A31: Venture Breakdown
A32: Metric | B32: Web Development | C32: Cinematic Videos | D32: Combined
A33: Leads | B33: =COUNTIFS('Master Leads'!$B$2:$B$201,"Web Development") -> 1 | C33: =COUNTIFS('Master Leads'!$B$2:$B$201,"Cinematic Videos") -> 1 | D33: =B33+C33 -> 2
A34: Outreach (contacted) | B34: =COUNTIFS('Master Leads'!$B$2:$B$201,"Web Development",'Master Leads'!$V$2:$V$201,"<>") -> 1 | C34: =COUNTIFS('Master Leads'!$B$2:$B$201,"Cinematic Videos",'Master Leads'!$V$2:$V$201,"<>") -> 1 | D34: =B34+C34 -> 2
A35: Positive replies | B35: =SUMPRODUCT(('Master Leads'!$B$2:$B$201="Web Development")*(ISNUMBER(MATCH('Master Leads'!$Y$2:$Y$201,{"Replied","Qualified","Preview Sent","Call Booked","Proposal Sent","Verbal Yes","Deposit Invoiced","Deposit Paid","Won"},0)))) -> 1 | C35: =SUMPRODUCT(('Master Leads'!$B$2:$B$201="Cinematic Videos")*(ISNUMBER(MATCH('Master Leads'!$Y$2:$Y$201,{"Replied","Qualified","Preview Sent","Call Booked","Proposal Sent","Verbal Yes","Deposit Invoiced","Deposit Paid","Won"},0)))) -> 1 | D35: =B35+C35 -> 2
A36: Calls | B36: =SUMPRODUCT(('Master Leads'!$B$2:$B$201="Web Development")*(ISNUMBER(MATCH('Master Leads'!$Y$2:$Y$201,{"Call Booked","Proposal Sent","Verbal Yes","Deposit Invoiced","Deposit Paid","Won"},0)))) -> 1 | C36: =SUMPRODUCT(('Master Leads'!$B$2:$B$201="Cinematic Videos")*(ISNUMBER(MATCH('Master Leads'!$Y$2:$Y$201,{"Call Booked","Proposal Sent","Verbal Yes","Deposit Invoiced","Deposit Paid","Won"},0)))) -> 1 | D36: =B36+C36 -> 2
A37: Proposals | B37: =SUMPRODUCT(('Master Leads'!$B$2:$B$201="Web Development")*(ISNUMBER(MATCH('Master Leads'!$Y$2:$Y$201,{"Proposal Sent","Verbal Yes","Deposit Invoiced","Deposit Paid","Won"},0)))) -> 1 | C37: =SUMPRODUCT(('Master Leads'!$B$2:$B$201="Cinematic Videos")*(ISNUMBER(MATCH('Master Leads'!$Y$2:$Y$201,{"Proposal Sent","Verbal Yes","Deposit Invoiced","Deposit Paid","Won"},0)))) -> 1 | D37: =B37+C37 -> 2
A38: Deals won | B38: =COUNTIFS('Master Leads'!$B$2:$B$201,"Web Development",'Master Leads'!$Y$2:$Y$201,"Won") -> 0 | C38: =COUNTIFS('Master Leads'!$B$2:$B$201,"Cinematic Videos",'Master Leads'!$Y$2:$Y$201,"Won") -> 0 | D38: =B38+C38 -> 0
A39: Pipeline value | B39: =SUMIFS('Master Leads'!$Z$2:$Z$201,'Master Leads'!$B$2:$B$201,"Web Development",'Master Leads'!$Y$2:$Y$201,"<>Won",'Master Leads'!$Y$2:$Y$201,"<>Lost") -> 1200 | C39: =SUMIFS('Master Leads'!$Z$2:$Z$201,'Master Leads'!$B$2:$B$201,"Cinematic Videos",'Master Leads'!$Y$2:$Y$201,"<>Won",'Master Leads'!$Y$2:$Y$201,"<>Lost") -> 1800 | D39: =B39+C39 -> 3000
A40: Contracted revenue | B40: =SUMIFS('Master Leads'!$Z$2:$Z$201,'Master Leads'!$B$2:$B$201,"Web Development",'Master Leads'!$Y$2:$Y$201,"Won") -> 0 | C40: =SUMIFS('Master Leads'!$Z$2:$Z$201,'Master Leads'!$B$2:$B$201,"Cinematic Videos",'Master Leads'!$Y$2:$Y$201,"Won") -> 0 | D40: =B40+C40 -> 0
A41: Cash collected | B41: 0 | C41: 0 | D41: =B41+C41 -> 0
A43: Note: 'Cash collected' cells (yellow) are the only manual inputs on this tab — update them weekly from the Payment Tracker's Totals. Every other figure recalculates automatically from Master Leads / Activities.

Sheet Web Development Dashboard
A1: Web Development Dashboard
A2: Venture-locked view — always filtered to Web Development
A4: Targets & Pricing (edit the yellow cells)
A5: Target contracted revenue | B5: 4000
A6: Target websites sold | B6: 4
A7: Standard website price | B7: 1200
A8: Launch-partner website price | B8: 1000
A9: Managed Hosting & Analytics (monthly) | B9: 39
A11: Pipeline & Activity Metrics
A12: Leads contacted | B12: =COUNTIFS('Master Leads'!$B$2:$B$201,"Web Development",'Master Leads'!$V$2:$V$201,"<>") -> 1
A13: Calls booked | B13: =SUMPRODUCT((('Master Leads'!$B$2:$B$201="Web Development"))*(ISNUMBER(MATCH('Master Leads'!$Y$2:$Y$201,{"Call Booked","Proposal Sent","Verbal Yes","Deposit Invoiced","Deposit Paid","Won"},0)))) -> 1
A14: Proposals sent | B14: =SUMPRODUCT((('Master Leads'!$B$2:$B$201="Web Development"))*(ISNUMBER(MATCH('Master Leads'!$Y$2:$Y$201,{"Proposal Sent","Verbal Yes","Deposit Invoiced","Deposit Paid","Won"},0)))) -> 1
A15: Websites sold (Won) | B15: =COUNTIFS('Master Leads'!$B$2:$B$201,"Web Development",'Master Leads'!$Y$2:$Y$201,"Won") -> 0
A16: Websites launched (manual — tick off in 04_Client_Delivery/Completed) | B16: 0
A17: Hosting subscriptions started (manual) | B17: 0
A18: Web Development pipeline (open deal value) | B18: =SUMIFS('Master Leads'!$Z$2:$Z$201,'Master Leads'!$B$2:$B$201,"Web Development",'Master Leads'!$Y$2:$Y$201,"<>Won",'Master Leads'!$Y$2:$Y$201,"<>Lost") -> 1200
A19: Contracted revenue | B19: =SUMIFS('Master Leads'!$Z$2:$Z$201,'Master Leads'!$B$2:$B$201,"Web Development",'Master Leads'!$Y$2:$Y$201,"Won") -> 0
A20: Cash collected (sync weekly from Payment Tracker) | B20: 0
A21: Progress against monthly revenue target | B21: =IFERROR($B$19/$B$5,0) -> 0
A22: Progress against target websites sold | B22: =IFERROR($B$15/$B$6,0) -> 0

Sheet Cinematic Videos Dashboard
A1: Cinematic Videos Dashboard
A2: Venture-locked view — always filtered to Cinematic Videos
A4: Targets & Pricing (edit the yellow cells)
A5: Target contracted revenue | B5: 4500
A6: Target deals | B6: 3
A7: Target average ticket | B7: 1500
A9: Pipeline & Activity Metrics
A10: Leads contacted | B10: =COUNTIFS('Master Leads'!$B$2:$B$201,"Cinematic Videos",'Master Leads'!$V$2:$V$201,"<>") -> 1
A11: Calls booked | B11: =SUMPRODUCT((('Master Leads'!$B$2:$B$201="Cinematic Videos"))*(ISNUMBER(MATCH('Master Leads'!$Y$2:$Y$201,{"Call Booked","Proposal Sent","Verbal Yes","Deposit Invoiced","Deposit Paid","Won"},0)))) -> 1
A12: Proposals sent | B12: =SUMPRODUCT((('Master Leads'!$B$2:$B$201="Cinematic Videos"))*(ISNUMBER(MATCH('Master Leads'!$Y$2:$Y$201,{"Proposal Sent","Verbal Yes","Deposit Invoiced","Deposit Paid","Won"},0)))) -> 1
A13: Video projects sold (Won) | B13: =COUNTIFS('Master Leads'!$B$2:$B$201,"Cinematic Videos",'Master Leads'!$Y$2:$Y$201,"Won") -> 0
A14: Video projects delivered (manual — tick off in 04_Client_Delivery/Completed) | B14: 0
A15: Cinematic Videos pipeline (open deal value) | B15: =SUMIFS('Master Leads'!$Z$2:$Z$201,'Master Leads'!$B$2:$B$201,"Cinematic Videos",'Master Leads'!$Y$2:$Y$201,"<>Won",'Master Leads'!$Y$2:$Y$201,"<>Lost") -> 1800
A16: Contracted revenue | B16: =SUMIFS('Master Leads'!$Z$2:$Z$201,'Master Leads'!$B$2:$B$201,"Cinematic Videos",'Master Leads'!$Y$2:$Y$201,"Won") -> 0
A17: Cash collected (sync weekly from Payment Tracker) | B17: 0
A18: Progress against monthly revenue target | B18: =IFERROR($B$16/$B$5,0) -> 0
A19: Progress against target deals | B19: =IFERROR($B$13/$B$6,0) -> 0

Sheet Master Leads
A1: Lead ID | B1: Venture | C1: Date Added | D1: Business Name | E1: Business Type | F1: Vertical | G1: Geography | H1: Website URL | I1: Contact Name | J1: Contact Role | K1: Email | L1: Phone | M1: WhatsApp | N1: Instagram | O1: LinkedIn | P1: Lead Source | Q1: Current Website or Marketing Problem | R1: Proposed Service | S1: Lead Tier | T1: Preview Type | U1: Preview Status | V1: First Outreach Date | W1: Last Contact Date | X1: Follow-Up Date | Y1: Pipeline Stage | Z1: Estimated Deal Value | AA1: Probability | AB1: Weighted Pipeline | AC1: Expected Close Date | AD1: Next Action | AE1: Next Action Date | AF1: Lost Reason | AG1: Notes
A2: LEAD-001 | B2: Web Development | C2: 46238 | D2: Example: Riverside Family Dental | E2: Dental Clinic | F2: Healthcare / Local Service | G2: Austin, TX | H2: www.example-riversidedental.com | I2: Dana Whitfield | J2: Practice Manager | K2: dana@example-riversidedental.com | L2: +1-512-555-0114 | M2: +1-512-555-0114 | N2: @riversidedental_example | O2: linkedin.com/in/example-dana | P2: Cold Email | Q2: Outdated 2014 site, not mobile-friendly, no online booking | R2: New 5-page responsive website + booking link | S2: A | T2: Website Homepage | U2: Sent | V2: 46239 | W2: 46253 | X2: 46281 | Y2: Proposal Sent | Z2: 1200 | AA2: =IFERROR(INDEX(Lists!$F$2:$F$15,MATCH(Y2,Lists!$E$2:$E$15,0)),"") -> 0.5 | AB2: =IF(OR(Z2="",AA2=""),"",Z2*AA2) -> 600 | AC2: 46291 | AD2: Follow up after proposal review call | AE2: Fictional example row — safe to delete.
A3: LEAD-002 | B3: Cinematic Videos | C3: 46245 | D3: Example: Bluestone Realty Group | E3: Real Estate Brokerage | F3: Real Estate | G3: Scottsdale, AZ | H3: www.example-bluestonerealty.com | I3: Marcus Ojeda | J3: Listing Agent | K3: marcus@example-bluestonerealty.com | L3: +1-480-555-0177 | M3: +1-480-555-0177 | N3: @bluestonerealty_example | O3: linkedin.com/in/example-marcus | P3: Instagram DM | Q3: Listing photos only, no cinematic video for $2M+ listings | R3: Cinematic property film for flagship listing | S3: A | T3: Cinematic Property Film | U3: Feedback Received | V3: 46246 | W3: 46267 | X3: 46280 | Y3: Verbal Yes | Z3: 1800 | AA3: =IFERROR(INDEX(Lists!$F$2:$F$15,MATCH(Y3,Lists!$E$2:$E$15,0)),"") -> 0.75 | AB3: =IF(OR(Z3="",AA3=""),"",Z3*AA3) -> 1350 | AC3: 46285 | AD3: Send contract + deposit invoice | AE3: Fictional example row — safe to delete.
AA4: =IFERROR(INDEX(Lists!$F$2:$F$15,MATCH(Y4,Lists!$E$2:$E$15,0)),"") | AB4: =IF(OR(Z4="",AA4=""),"",Z4*AA4)
AA5: =IFERROR(INDEX(Lists!$F$2:$F$15,MATCH(Y5,Lists!$E$2:$E$15,0)),"") | AB5: =IF(OR(Z5="",AA5=""),"",Z5*AA5)
AA6: =IFERROR(INDEX(Lists!$F$2:$F$15,MATCH(Y6,Lists!$E$2:$E$15,0)),"") | AB6: =IF(OR(Z6="",AA6=""),"",Z6*AA6)
AA7: =IFERROR(INDEX(Lists!$F$2:$F$15,MATCH(Y7,Lists!$E$2:$E$15,0)),"") | AB7: =IF(OR(Z7="",AA7=""),"",Z7*AA7)
AA8: =IFERROR(INDEX(Lists!$F$2:$F$15,MATCH(Y8,Lists!$E$2:$E$15,0)),"") | AB8: =IF(OR(Z8="",AA8=""),"",Z8*AA8)
AA9: =IFERROR(INDEX(Lists!$F$2:$F$15,MATCH(Y9,Lists!$E$2:$E$15,0)),"") | AB9: =IF(OR(Z9="",AA9=""),"",Z9*AA9)
AA10: =IFERROR(INDEX(Lists!$F$2:$F$15,MATCH(Y10,Lists!$E$2:$E$15,0)),"") | AB10: =IF(OR(Z10="",AA10=""),"",Z10*AA10)
AA11: =IFERROR(INDEX(Lists!$F$2:$F$15,MATCH(Y11,Lists!$E$2:$E$15,0)),"") | AB11: =IF(OR(Z11="",AA11=""),"",Z11*AA11)
AA12: =IFERROR(INDEX(Lists!$F$2:$F$15,MATCH(Y12,Lists!$E$2:$E$15,0)),"") | AB12: =IF(OR(Z12="",AA12=""),"",Z12*AA12)
AA13: =IFERROR(INDEX(Lists!$F$2:$F$15,MATCH(Y13,Lists!$E$2:$E$15,0)),"") | AB13: =IF(OR(Z13="",AA13=""),"",Z13*AA13)
AA14: =IFERROR(INDEX(Lists!$F$2:$F$15,MATCH(Y14,Lists!$E$2:$E$15,0)),"") | AB14: =IF(OR(Z14="",AA14=""),"",Z14*AA14)
AA15: =IFERROR(INDEX(Lists!$F$2:$F$15,MATCH(Y15,Lists!$E$2:$E$15,0)),"") | AB15: =IF(OR(Z15="",AA15=""),"",Z15*AA15)
... AA201: =IFERROR(INDEX(Lists!$F$2:$F$15,MATCH(Y201,Lists!$E$2:$E$15,0)),"") | AB201: =IF(OR(Z201="",AA201=""),"",Z201*AA201)

Sheet Activities
A1: Activity ID | B1: Date | C1: Lead ID | D1: Venture | E1: Business Name | F1: Contact Name | G1: Activity Type | H1: Notes | I1: Outcome | J1: Next Action | K1: Next Action Date | L1: Completed By
A2: ACT-001 | B2: 46291 | C2: LEAD-001 | D2: =IFERROR(INDEX('Master Leads'!$B$2:$B$201,MATCH(C2,'Master Leads'!$A$2:$A$201,0)),"") -> Web Development | E2: =IFERROR(INDEX('Master Leads'!$D$2:$D$201,MATCH(C2,'Master Leads'!$A$2:$A$201,0)),"") -> Example: Riverside Family Dental | F2: Dana Whitfield | G2: Proposal Sent | H2: Emailed website proposal PROP-001 with homepage preview link. | I2: Awaiting review | J2: Call to walk through proposal | K2: 46294 | L2: You
A3: ACT-002 | B3: 46267 | C3: LEAD-002 | D3: =IFERROR(INDEX('Master Leads'!$B$2:$B$201,MATCH(C3,'Master Leads'!$A$2:$A$201,0)),"") -> Cinematic Videos | E3: =IFERROR(INDEX('Master Leads'!$D$2:$D$201,MATCH(C3,'Master Leads'!$A$2:$A$201,0)),"") -> Example: Bluestone Realty Group | F3: Marcus Ojeda | G3: Preview Sent | H3: Sent 45s cinematic preview cut of flagship listing via WeTransfer. | I3: Loved the preview | J3: Send full proposal + contract | K3: 46270 | L3: You
D4: =IFERROR(INDEX('Master Leads'!$B$2:$B$201,MATCH(C4,'Master Leads'!$A$2:$A$201,0)),"") | E4: =IFERROR(INDEX('Master Leads'!$D$2:$D$201,MATCH(C4,'Master Leads'!$A$2:$A$201,0)),"")
D5: =IFERROR(INDEX('Master Leads'!$B$2:$B$201,MATCH(C5,'Master Leads'!$A$2:$A$201,0)),"") | E5: =IFERROR(INDEX('Master Leads'!$D$2:$D$201,MATCH(C5,'Master Leads'!$A$2:$A$201,0)),"")
D6: =IFERROR(INDEX('Master Leads'!$B$2:$B$201,MATCH(C6,'Master Leads'!$A$2:$A$201,0)),"") | E6: =IFERROR(INDEX('Master Leads'!$D$2:$D$201,MATCH(C6,'Master Leads'!$A$2:$A$201,0)),"")
D7: =IFERROR(INDEX('Master Leads'!$B$2:$B$201,MATCH(C7,'Master Leads'!$A$2:$A$201,0)),"") | E7: =IFERROR(INDEX('Master Leads'!$D$2:$D$201,MATCH(C7,'Master Leads'!$A$2:$A$201,0)),"")
D8: =IFERROR(INDEX('Master Leads'!$B$2:$B$201,MATCH(C8,'Master Leads'!$A$2:$A$201,0)),"") | E8: =IFERROR(INDEX('Master Leads'!$D$2:$D$201,MATCH(C8,'Master Leads'!$A$2:$A$201,0)),"")
D9: =IFERROR(INDEX('Master Leads'!$B$2:$B$201,MATCH(C9,'Master Leads'!$A$2:$A$201,0)),"") | E9: =IFERROR(INDEX('Master Leads'!$D$2:$D$201,MATCH(C9,'Master Leads'!$A$2:$A$201,0)),"")
D10: =IFERROR(INDEX('Master Leads'!$B$2:$B$201,MATCH(C10,'Master Leads'!$A$2:$A$201,0)),"") | E10: =IFERROR(INDEX('Master Leads'!$D$2:$D$201,MATCH(C10,'Master Leads'!$A$2:$A$201,0)),"")
D11: =IFERROR(INDEX('Master Leads'!$B$2:$B$201,MATCH(C11,'Master Leads'!$A$2:$A$201,0)),"") | E11: =IFERROR(INDEX('Master Leads'!$D$2:$D$201,MATCH(C11,'Master Leads'!$A$2:$A$201,0)),"")
D12: =IFERROR(INDEX('Master Leads'!$B$2:$B$201,MATCH(C12,'Master Leads'!$A$2:$A$201,0)),"") | E12: =IFERROR(INDEX('Master Leads'!$D$2:$D$201,MATCH(C12,'Master Leads'!$A$2:$A$201,0)),"")
D13: =IFERROR(INDEX('Master Leads'!$B$2:$B$201,MATCH(C13,'Master Leads'!$A$2:$A$201,0)),"") | E13: =IFERROR(INDEX('Master Leads'!$D$2:$D$201,MATCH(C13,'Master Leads'!$A$2:$A$201,0)),"")
D14: =IFERROR(INDEX('Master Leads'!$B$2:$B$201,MATCH(C14,'Master Leads'!$A$2:$A$201,0)),"") | E14: =IFERROR(INDEX('Master Leads'!$D$2:$D$201,MATCH(C14,'Master Leads'!$A$2:$A$201,0)),"")
D15: =IFERROR(INDEX('Master Leads'!$B$2:$B$201,MATCH(C15,'Master Leads'!$A$2:$A$201,0)),"") | E15: =IFERROR(INDEX('Master Leads'!$D$2:$D$201,MATCH(C15,'Master Leads'!$A$2:$A$201,0)),"")
... D201: =IFERROR(INDEX('Master Leads'!$B$2:$B$201,MATCH(C201,'Master Leads'!$A$2:$A$201,0)),"") | E201: =IFERROR(INDEX('Master Leads'!$D$2:$D$201,MATCH(C201,'Master Leads'!$A$2:$A$201,0)),"")

Sheet Lists
A1: Venture | B1: LeadTier | C1: PreviewType | D1: PreviewStatus | E1: PipelineStage | F1: Probability | G1: ActivityType | H1: VentureFilter | I1: PaymentStatus
A2: Web Development | B2: A | C2: Website Homepage | D2: Not Required | E2: Identified | F2: 0.05 | G2: Cold Email | H2: All | I2: Not Invoiced
A3: Cinematic Videos | B3: B | C3: Website Audit | D3: To Create | E3: Contacted | F3: 0.1 | G3: Follow-Up Email | H3: Web Development | I3: Invoiced
B4: C | C4: Cinematic Property Film | D4: In Progress | E4: Follow-Up | F4: 0.1 | G4: Call | H4: Cinematic Videos | I4: Paid
C5: Cinematic Location Film | D5: Ready | E5: Replied | F5: 0.2 | G5: WhatsApp | I5: Overdue
C6: Before-and-After Concept | D6: Sent | E6: Qualified | F6: 0.25 | G6: LinkedIn | I6: Waived
C7: None | D7: Viewed | E7: Preview Sent | F7: 0.35 | G7: Instagram DM
D8: Feedback Received | E8: Call Booked | F8: 0.4 | G8: Preview Created
E9: Proposal Sent | F9: 0.5 | G9: Preview Sent
E10: Verbal Yes | F10: 0.75 | G10: Proposal Sent
E11: Deposit Invoiced | F11: 0.85 | G11: Payment Reminder
E12: Deposit Paid | F12: 0.95 | G12: Client Meeting
E13: Won | F13: 1 | G13: Other
E14: Lost | F14: 0
E15: Nurture | F15: 0.05
